zenmake/__init__.py
zenmake/__main__.py
zenmake/version
zenmake/zmrun.py
zenmake/thirdparty/__init__.py
zenmake/thirdparty/argparse/LICENSE.txt
zenmake/thirdparty/argparse/NEWS.txt
zenmake/thirdparty/argparse/__init__.py
zenmake/thirdparty/argparse/argparse.py
zenmake/thirdparty/pyyaml/CHANGES
zenmake/thirdparty/pyyaml/LICENSE
zenmake/thirdparty/pyyaml/yaml/__init__.py
zenmake/thirdparty/pyyaml/yaml/composer.py
zenmake/thirdparty/pyyaml/yaml/constructor.py
zenmake/thirdparty/pyyaml/yaml/cyaml.py
zenmake/thirdparty/pyyaml/yaml/dumper.py
zenmake/thirdparty/pyyaml/yaml/emitter.py
zenmake/thirdparty/pyyaml/yaml/error.py
zenmake/thirdparty/pyyaml/yaml/events.py
zenmake/thirdparty/pyyaml/yaml/loader.py
zenmake/thirdparty/pyyaml/yaml/nodes.py
zenmake/thirdparty/pyyaml/yaml/parser.py
zenmake/thirdparty/pyyaml/yaml/reader.py
zenmake/thirdparty/pyyaml/yaml/representer.py
zenmake/thirdparty/pyyaml/yaml/resolver.py
zenmake/thirdparty/pyyaml/yaml/scanner.py
zenmake/thirdparty/pyyaml/yaml/serializer.py
zenmake/thirdparty/pyyaml/yaml/tokens.py
zenmake/waf/waf-light
zenmake/waf/waflib/Build.py
zenmake/waf/waflib/ConfigSet.py
zenmake/waf/waflib/Configure.py
zenmake/waf/waflib/Context.py
zenmake/waf/waflib/Errors.py
zenmake/waf/waflib/Logs.py
zenmake/waf/waflib/Node.py
zenmake/waf/waflib/Options.py
zenmake/waf/waflib/Runner.py
zenmake/waf/waflib/Scripting.py
zenmake/waf/waflib/Task.py
zenmake/waf/waflib/TaskGen.py
zenmake/waf/waflib/Utils.py
zenmake/waf/waflib/__init__.py
zenmake/waf/waflib/ansiterm.py
zenmake/waf/waflib/fixpy2.py
zenmake/waf/waflib/processor.py
zenmake/waf/waflib/Tools/__init__.py
zenmake/waf/waflib/Tools/ar.py
zenmake/waf/waflib/Tools/asm.py
zenmake/waf/waflib/Tools/bison.py
zenmake/waf/waflib/Tools/c.py
zenmake/waf/waflib/Tools/c_aliases.py
zenmake/waf/waflib/Tools/c_config.py
zenmake/waf/waflib/Tools/c_osx.py
zenmake/waf/waflib/Tools/c_preproc.py
zenmake/waf/waflib/Tools/c_tests.py
zenmake/waf/waflib/Tools/ccroot.py
zenmake/waf/waflib/Tools/clang.py
zenmake-0.11.0.dist-info/LICENSE
zenmake-0.11.0.dist-info/METADATA
zenmake-0.11.0.dist-info/WHEEL
zenmake-0.11.0.dist-info/entry_points.txt
zenmake-0.11.0.dist-info/top_level.txt
zenmake-0.11.0.dist-info/RECORD
