Metadata-Version: 2.1
Name: zenmake
Version: 0.11.0
Summary: ZenMake - build system based on the WAF
Home-page: https://github.com/pustotnik/zenmake
Author: Alexander Magola
Author-email: pustotnik@gmail.com
License: BSD
Project-URL: Bug Tracker, https://github.com/pustotnik/zenmake/issues
Project-URL: Source Code, https://github.com/pustotnik/zenmake
Project-URL: Documentation, https://zenmake.readthedocs.io
Platform: UNKNOWN
Classifier: Development Status :: 4 - Beta
Classifier: License :: OSI Approved :: BSD License
Classifier: Environment :: Console
Classifier: Intended Audience :: Developers
Classifier: Programming Language :: Python
Classifier: Programming Language :: Python :: 3 :: Only
Classifier: Programming Language :: Python :: 3.5
Classifier: Programming Language :: Python :: 3.6
Classifier: Programming Language :: Python :: 3.7
Classifier: Programming Language :: Python :: 3.8
Classifier: Programming Language :: Python :: 3.9
Classifier: Programming Language :: Python :: 3.10
Classifier: Programming Language :: Python :: Implementation :: CPython
Classifier: Operating System :: POSIX :: Linux
Classifier: Operating System :: MacOS
Classifier: Operating System :: Microsoft :: Windows
Classifier: Topic :: Software Development :: Build Tools
Requires-Python: >=3.5
License-File: LICENSE
Requires-Dist: PyYAML
